LICENSE.rst
centralauth/__init__.py
centralauth/client/__init__.py
centralauth/client/apps.py
centralauth/client/backends.py
centralauth/client/constants.py
centralauth/client/locale/de/LC_MESSAGES/django.mo
centralauth/client/locale/de/LC_MESSAGES/django.po
centralauth/client/management/__init__.py
centralauth/client/management/commands/__init__.py
centralauth/client/management/commands/sync_perms.py
centralauth/client/middleware.py
centralauth/client/services.py
centralauth/client/templates/centralauth/client/client_login.html
centralauth/client/urls.py
centralauth/client/views.py
centralauth/compat.py
centralauth/provider/__init__.py
centralauth/provider/admin.py
centralauth/provider/apps.py
centralauth/provider/locale/de/LC_MESSAGES/django.mo
centralauth/provider/locale/de/LC_MESSAGES/django.po
centralauth/provider/migrations/0001_initial.py
centralauth/provider/migrations/0002_auto_20181107_0932.py
centralauth/provider/migrations/0003_auto_20181114_1350.py
centralauth/provider/migrations/0004_auto_20181120_2331.py
centralauth/provider/migrations/__init__.py
centralauth/provider/models.py
centralauth/provider/oauth2_backends.py
centralauth/provider/oauth_urls.py
centralauth/provider/urls.py
centralauth/provider/views.py
django_centralauth-2.0.0.dist-info/LICENSE.rst
django_centralauth-2.0.0.dist-info/WHEEL
django_centralauth-2.0.0.dist-info/METADATA
django_centralauth-2.0.0.dist-info/RECORD
