Metadata-Version: 2.1
Name: django-centralauth
Version: 2.0.0
Summary: App for managing user access and permissions from multiple projects.
Home-page: https://github.com/lenarother/django-centralauth
License: MIT
Author: Magdalena Rother
Author-email: rother.magdalena@gmail.com
Requires-Python: >=3.6,<4
Classifier: Development Status :: 5 - Production/Stable
Classifier: Environment :: Web Environment
Classifier: Framework :: Django
Classifier: Intended Audience :: Developers
Classifier: License :: OSI Approved :: MIT License
Classifier: Operating System :: Unix
Classifier: Programming Language :: Python
Classifier: Programming Language :: Python :: 3
Classifier: Programming Language :: Python :: 3.6
Classifier: Programming Language :: Python :: 3.7
Classifier: Programming Language :: Python :: 3.8
Classifier: Programming Language :: Python :: 3.9
Provides-Extra: docs
Requires-Dist: Django (>=2.2)
Requires-Dist: Sphinx (>=3.5); extra == "docs"
Requires-Dist: django-oauth-toolkit (>=1.5)
Requires-Dist: importlib-metadata; python_version < "3.8"
Requires-Dist: requests (>=2.25)
Requires-Dist: requests-oauthlib (>=1.3)
Project-URL: Repository, https://github.com/lenarother/django-centralauth
